youtube_bz/__init__.py
youtube_bz/__main__.py
youtube_bz/exceptions.py
youtube_bz/main.py
youtube_bz/api/__init__.py
youtube_bz/api/musicbrainz/__init__.py
youtube_bz/api/musicbrainz/api.py
youtube_bz/api/youtube/__init__.py
youtube_bz/api/youtube/api.py
youtube_bz/api/youtube/exceptions.py
youtube_bz/commands/__init__.py
youtube_bz/commands/download.py
youtube_bz/commands/search.py
youtube_bz/utils/__init__.py
youtube_bz/utils/levenshtein_distance.py
youtube_bz-0.5.1.dist-info/METADATA
youtube_bz-0.5.1.dist-info/WHEEL
youtube_bz-0.5.1.dist-info/entry_points.txt
youtube_bz-0.5.1.dist-info/licenses/LICENSE
youtube_bz-0.5.1.dist-info/RECORD
