Metadata-Version: 2.1
Name: youtube-bz
Version: 0.5.1
Summary: YoutubeBrainz allow you to find and download Youtube Videos associated to an Album on MusicBrainz.
Author-email: Flowrey <flowrey@laposte.net>
License-Expression: GPL-3.0
License-File: LICENSE
Requires-Dist: pytube>=15.0.0
Requires-Dist: rich>=13.6.0
